ttp_templates/__init__.py
ttp_templates/misc/N2G/cli_ip_data/a10.txt
ttp_templates/misc/N2G/cli_ip_data/arista_eos.txt
ttp_templates/misc/N2G/cli_ip_data/cisco_ios.txt
ttp_templates/misc/N2G/cli_ip_data/cisco_nxos.txt
ttp_templates/misc/N2G/cli_ip_data/cisco_xr.txt
ttp_templates/misc/N2G/cli_ip_data/fortinet.txt
ttp_templates/misc/N2G/cli_ip_data/huawei.txt
ttp_templates/misc/N2G/cli_ip_data/readme.md
ttp_templates/misc/N2G/cli_isis_data/cisco_xr.txt
ttp_templates/misc/N2G/cli_isis_data/juniper.txt
ttp_templates/misc/N2G/cli_isis_data/readme.md
ttp_templates/misc/N2G/cli_l2_data/cisco_ios.txt
ttp_templates/misc/N2G/cli_l2_data/cisco_nxos.txt
ttp_templates/misc/N2G/cli_l2_data/cisco_xr.txt
ttp_templates/misc/N2G/cli_l2_data/huawei.txt
ttp_templates/misc/N2G/cli_l2_data/juniper.txt
ttp_templates/misc/N2G/cli_l2_data/readme.md
ttp_templates/misc/N2G/cli_ospf_data/cisco_ios.txt
ttp_templates/misc/N2G/cli_ospf_data/cisco_xr.txt
ttp_templates/misc/N2G/cli_ospf_data/huawei.txt
ttp_templates/misc/N2G/cli_ospf_data/readme.md
ttp_templates/misc/Netbox/parse_arista_eos_config.txt
ttp_templates/misc/Netbox/parse_cisco_xr_config.txt
ttp_templates/misc/Netbox/parse_juniper_junos_config.txt
ttp_templates/misc/Netmiko/cisco.ios.arp.txt
ttp_templates/misc/Netmiko/cisco.ios.cfg.bgp.txt
ttp_templates/misc/Netmiko/cisco.ios.cfg.interface.txt
ttp_templates/misc/Netmiko/cisco.ios.cfg.ip.txt
ttp_templates/misc/Netmiko/cisco.ios.cfg.nat.static.txt
ttp_templates/misc/Netmiko/cisco.iosxr.arp.txt
ttp_templates/misc/Netmiko/cisco.iosxr.cfg.interface.txt
ttp_templates/misc/Netmiko/cisco.iosxr.cfg.ip.txt
ttp_templates/misc/Netmiko/huawei.vrp.cfg.interface.txt
ttp_templates/misc/Netmiko/huawei.vrp.cfg.ip.txt
ttp_templates/misc/ttp_templates_tests/cisco_ios_interfaces_cfg_per_ip.txt
ttp_templates/misc/ttp_templates_tests/netmiko_cisco_ios_interfaces.txt
ttp_templates/platform/arista_eos_show_hostname.txt
ttp_templates/platform/cisco_ios_show_ip_arp.txt
ttp_templates-0.3.4.dist-info/LICENSE
ttp_templates-0.3.4.dist-info/WHEEL
ttp_templates-0.3.4.dist-info/METADATA
ttp_templates-0.3.4.dist-info/RECORD
