Metadata-Version: 2.1
Name: ttp-templates
Version: 0.3.4
Summary: Template Text Parser Templates collections
Home-page: https://github.com/dmulyalin/ttp_templates
License: MIT
Keywords: Parsing,TTP,regex
Author: Denis Mulyalin
Author-email: d.mulyalin@gmail.com
Maintainer: Denis Mulyalin
Maintainer-email: d.mulyalin@gmail.com
Requires-Python: >=3.6,<4.0
Classifier: License :: OSI Approved :: MIT License
Classifier: Operating System :: POSIX :: Linux
Classifier: Programming Language :: Python :: 2.7
Classifier: Programming Language :: Python :: 3
Classifier: Programming Language :: Python :: 3.10
Classifier: Programming Language :: Python :: 3.6
Classifier: Programming Language :: Python :: 3.7
Classifier: Programming Language :: Python :: 3.8
Classifier: Programming Language :: Python :: 3.9
Classifier: Topic :: Utilities
Provides-Extra: docs
Requires-Dist: mkdocs (==1.2.4); (python_version >= "3.7") and (extra == "docs")
Requires-Dist: mkdocs-material (==7.2.2); (python_version >= "3.7") and (extra == "docs")
Requires-Dist: mkdocs-material-extensions (==1.0.1); (python_version >= "3.7") and (extra == "docs")
Requires-Dist: mkdocstrings[python] (>=0.18.0,<0.19.0); (python_version >= "3.7") and (extra == "docs")
Requires-Dist: pygments (==2.11); (python_version >= "3.7") and (extra == "docs")
Requires-Dist: pymdown-extensions (==9.3); (python_version >= "3.7") and (extra == "docs")
Requires-Dist: ttp (>=0.6.0)
Project-URL: Documentation, https://dmulyalin.github.io/ttp_templates/
Project-URL: Repository, https://github.com/dmulyalin/ttp_templates
